{
  "db_name": "SQLite",
  "query": "SELECT \n                id as \"id!\", order_number as \"order_number!: i32\", customer_id as \"customer_id!\", \n                customer_vehicle_id as \"customer_vehicle_id!\", vehicle_year_id as \"vehicle_year_id!\", \n                employee_id as \"employee_id!\",\n                vehicle_km as \"vehicle_km?: i32\", symptoms as \"symptoms?\", diagnosis as \"diagnosis?\",\n                status as \"status!\", labor_cost as \"labor_cost!\", parts_cost as \"parts_cost!\", \n                discount as \"discount!\", total as \"total!\", warranty_days as \"warranty_days!: i32\",\n                warranty_until as \"warranty_until?\", scheduled_date as \"scheduled_date?\",\n                started_at as \"started_at?\", completed_at as \"completed_at?\",\n                payment_method as \"payment_method?\", is_paid as \"is_paid!: bool\",\n                notes as \"notes?\", internal_notes as \"internal_notes?\",\n                created_at as \"created_at!\", updated_at as \"updated_at!\"\n            FROM service_orders WHERE order_number = ?",
  "describe": {
    "columns": [
      {
        "name": "id!",
        "ordinal": 0,
        "type_info": "Text"
      },
      {
        "name": "order_number!: i32",
        "ordinal": 1,
        "type_info": "Integer"
      },
      {
        "name": "customer_id!",
        "ordinal": 2,
        "type_info": "Text"
      },
      {
        "name": "customer_vehicle_id!",
        "ordinal": 3,
        "type_info": "Text"
      },
      {
        "name": "vehicle_year_id!",
        "ordinal": 4,
        "type_info": "Text"
      },
      {
        "name": "employee_id!",
        "ordinal": 5,
        "type_info": "Text"
      },
      {
        "name": "vehicle_km?: i32",
        "ordinal": 6,
        "type_info": "Integer"
      },
      {
        "name": "symptoms?",
        "ordinal": 7,
        "type_info": "Text"
      },
      {
        "name": "diagnosis?",
        "ordinal": 8,
        "type_info": "Text"
      },
      {
        "name": "status!",
        "ordinal": 9,
        "type_info": "Text"
      },
      {
        "name": "labor_cost!",
        "ordinal": 10,
        "type_info": "Float"
      },
      {
        "name": "parts_cost!",
        "ordinal": 11,
        "type_info": "Float"
      },
      {
        "name": "discount!",
        "ordinal": 12,
        "type_info": "Float"
      },
      {
        "name": "total!",
        "ordinal": 13,
        "type_info": "Float"
      },
      {
        "name": "warranty_days!: i32",
        "ordinal": 14,
        "type_info": "Integer"
      },
      {
        "name": "warranty_until?",
        "ordinal": 15,
        "type_info": "Text"
      },
      {
        "name": "scheduled_date?",
        "ordinal": 16,
        "type_info": "Text"
      },
      {
        "name": "started_at?",
        "ordinal": 17,
        "type_info": "Text"
      },
      {
        "name": "completed_at?",
        "ordinal": 18,
        "type_info": "Text"
      },
      {
        "name": "payment_method?",
        "ordinal": 19,
        "type_info": "Text"
      },
      {
        "name": "is_paid!: bool",
        "ordinal": 20,
        "type_info": "Integer"
      },
      {
        "name": "notes?",
        "ordinal": 21,
        "type_info": "Text"
      },
      {
        "name": "internal_notes?",
        "ordinal": 22,
        "type_info": "Text"
      },
      {
        "name": "created_at!",
        "ordinal": 23,
        "type_info": "Text"
      },
      {
        "name": "updated_at!",
        "ordinal": 24,
        "type_info": "Text"
      }
    ],
    "parameters": {
      "Right": 1
    },
    "nullable": [
      true,
      false,
      false,
      false,
      false,
      false,
      true,
      true,
      true,
      false,
      false,
      false,
      false,
      false,
      false,
      true,
      true,
      true,
      true,
      true,
      false,
      true,
      true,
      false,
      false
    ]
  },
  "hash": "d55f6d00b0290c821b941dad69e1a8e9e57b75425db2eadb10e9ee7a308d1057"
}
