[
  {
    "name": "@giro/desktop",
    "version": "1.0.19",
    "path": "/home/jhonslife/CICLOGIRO/GIRO/apps/desktop",
    "private": true,
    "dependencies": {
      "@hookform/resolvers": {
        "from": "@hookform/resolvers",
        "version": "3.10.0",
        "resolved": "https://registry.npmjs.org/@hookform/resolvers/-/resolvers-3.10.0.tgz",
        "path": "/home/jhonslife/CICLOGIRO/GIRO/node_modules/.pnpm/@hookform+resolvers@3.10.0_react-hook-form@7.71.1_react@18.3.1_/node_modules/@hookform/resolvers"
      },
      "@radix-ui/react-alert-dialog": {
        "from": "@radix-ui/react-alert-dialog",
        "version": "1.1.15",
        "resolved": "https://registry.npmjs.org/@radix-ui/react-alert-dialog/-/react-alert-dialog-1.1.15.tgz",
        "path": "/home/jhonslife/CICLOGIRO/GIRO/node_modules/.pnpm/@radix-ui+react-alert-dialog@1.1.15_@types+react-dom@18.3.7_@types+react@18.3.27__@type_2938e8bb4531c18dd665808ca65dbf8b/node_modules/@radix-ui/react-alert-dialog"
      },
      "@radix-ui/react-avatar": {
        "from": "@radix-ui/react-avatar",
        "version": "1.1.11",
        "resolved": "https://registry.npmjs.org/@radix-ui/react-avatar/-/react-avatar-1.1.11.tgz",
        "path": "/home/jhonslife/CICLOGIRO/GIRO/node_modules/.pnpm/@radix-ui+react-avatar@1.1.11_@types+react-dom@18.3.7_@types+react@18.3.27__@types+reac_5f98ab88aaa31d5c2a223f717db04a0c/node_modules/@radix-ui/react-avatar"
      },
      "@radix-ui/react-checkbox": {
        "from": "@radix-ui/react-checkbox",
        "version": "1.3.3",
        "resolved": "https://registry.npmjs.org/@radix-ui/react-checkbox/-/react-checkbox-1.3.3.tgz",
        "path": "/home/jhonslife/CICLOGIRO/GIRO/node_modules/.pnpm/@radix-ui+react-checkbox@1.3.3_@types+react-dom@18.3.7_@types+react@18.3.27__@types+rea_66165bf08e66a700b29af965a6554b6d/node_modules/@radix-ui/react-checkbox"
      },
      "@radix-ui/react-dialog": {
        "from": "@radix-ui/react-dialog",
        "version": "1.1.15",
        "resolved": "https://registry.npmjs.org/@radix-ui/react-dialog/-/react-dialog-1.1.15.tgz",
        "path": "/home/jhonslife/CICLOGIRO/GIRO/node_modules/.pnpm/@radix-ui+react-dialog@1.1.15_@types+react-dom@18.3.7_@types+react@18.3.27__@types+reac_714ecc194868bb6245bac079a4c1dd41/node_modules/@radix-ui/react-dialog"
      },
      "@radix-ui/react-dropdown-menu": {
        "from": "@radix-ui/react-dropdown-menu",
        "version": "2.1.16",
        "resolved": "https://registry.npmjs.org/@radix-ui/react-dropdown-menu/-/react-dropdown-menu-2.1.16.tgz",
        "path": "/home/jhonslife/CICLOGIRO/GIRO/node_modules/.pnpm/@radix-ui+react-dropdown-menu@2.1.16_@types+react-dom@18.3.7_@types+react@18.3.27__@typ_ae8057baf24490fce8ac6bda74ed442f/node_modules/@radix-ui/react-dropdown-menu"
      },
      "@radix-ui/react-label": {
        "from": "@radix-ui/react-label",
        "version": "2.1.8",
        "resolved": "https://registry.npmjs.org/@radix-ui/react-label/-/react-label-2.1.8.tgz",
        "path": "/home/jhonslife/CICLOGIRO/GIRO/node_modules/.pnpm/@radix-ui+react-label@2.1.8_@types+react-dom@18.3.7_@types+react@18.3.27__@types+react@_f9fd656c7e25d0f098a7f09db9ff7e4d/node_modules/@radix-ui/react-label"
      },
      "@radix-ui/react-popover": {
        "from": "@radix-ui/react-popover",
        "version": "1.1.15",
        "resolved": "https://registry.npmjs.org/@radix-ui/react-popover/-/react-popover-1.1.15.tgz",
        "path": "/home/jhonslife/CICLOGIRO/GIRO/node_modules/.pnpm/@radix-ui+react-popover@1.1.15_@types+react-dom@18.3.7_@types+react@18.3.27__@types+rea_f414476ba668d1d3d4761b013b1df312/node_modules/@radix-ui/react-popover"
      },
      "@radix-ui/react-progress": {
        "from": "@radix-ui/react-progress",
        "version": "1.1.8",
        "resolved": "https://registry.npmjs.org/@radix-ui/react-progress/-/react-progress-1.1.8.tgz",
        "path": "/home/jhonslife/CICLOGIRO/GIRO/node_modules/.pnpm/@radix-ui+react-progress@1.1.8_@types+react-dom@18.3.7_@types+react@18.3.27__@types+rea_b47b4570aad745051fbd4cf26abb1448/node_modules/@radix-ui/react-progress"
      },
      "@radix-ui/react-scroll-area": {
        "from": "@radix-ui/react-scroll-area",
        "version": "1.2.10",
        "resolved": "https://registry.npmjs.org/@radix-ui/react-scroll-area/-/react-scroll-area-1.2.10.tgz",
        "path": "/home/jhonslife/CICLOGIRO/GIRO/node_modules/.pnpm/@radix-ui+react-scroll-area@1.2.10_@types+react-dom@18.3.7_@types+react@18.3.27__@types_5bcbc5a51cd2460e88b2b8df9637afcd/node_modules/@radix-ui/react-scroll-area"
      },
      "@radix-ui/react-select": {
        "from": "@radix-ui/react-select",
        "version": "2.2.6",
        "resolved": "https://registry.npmjs.org/@radix-ui/react-select/-/react-select-2.2.6.tgz",
        "path": "/home/jhonslife/CICLOGIRO/GIRO/node_modules/.pnpm/@radix-ui+react-select@2.2.6_@types+react-dom@18.3.7_@types+react@18.3.27__@types+react_42a61fabe7791626d795a1c936413a8c/node_modules/@radix-ui/react-select"
      },
      "@radix-ui/react-separator": {
        "from": "@radix-ui/react-separator",
        "version": "1.1.8",
        "resolved": "https://registry.npmjs.org/@radix-ui/react-separator/-/react-separator-1.1.8.tgz",
        "path": "/home/jhonslife/CICLOGIRO/GIRO/node_modules/.pnpm/@radix-ui+react-separator@1.1.8_@types+react-dom@18.3.7_@types+react@18.3.27__@types+re_ee869837196e551570ae29ebefcce290/node_modules/@radix-ui/react-separator"
      },
      "@radix-ui/react-slot": {
        "from": "@radix-ui/react-slot",
        "version": "1.2.4",
        "resolved": "https://registry.npmjs.org/@radix-ui/react-slot/-/react-slot-1.2.4.tgz",
        "path": "/home/jhonslife/CICLOGIRO/GIRO/node_modules/.pnpm/@radix-ui+react-slot@1.2.4_@types+react@18.3.27_react@18.3.1/node_modules/@radix-ui/react-slot"
      },
      "@radix-ui/react-switch": {
        "from": "@radix-ui/react-switch",
        "version": "1.2.6",
        "resolved": "https://registry.npmjs.org/@radix-ui/react-switch/-/react-switch-1.2.6.tgz",
        "path": "/home/jhonslife/CICLOGIRO/GIRO/node_modules/.pnpm/@radix-ui+react-switch@1.2.6_@types+react-dom@18.3.7_@types+react@18.3.27__@types+react_6c7094978be4077983b7d6e412b585b9/node_modules/@radix-ui/react-switch"
      },
      "@radix-ui/react-tabs": {
        "from": "@radix-ui/react-tabs",
        "version": "1.1.13",
        "resolved": "https://registry.npmjs.org/@radix-ui/react-tabs/-/react-tabs-1.1.13.tgz",
        "path": "/home/jhonslife/CICLOGIRO/GIRO/node_modules/.pnpm/@radix-ui+react-tabs@1.1.13_@types+react-dom@18.3.7_@types+react@18.3.27__@types+react@_0aaeef7d22accbb55e056dc5f51b50fa/node_modules/@radix-ui/react-tabs"
      },
      "@radix-ui/react-toast": {
        "from": "@radix-ui/react-toast",
        "version": "1.2.15",
        "resolved": "https://registry.npmjs.org/@radix-ui/react-toast/-/react-toast-1.2.15.tgz",
        "path": "/home/jhonslife/CICLOGIRO/GIRO/node_modules/.pnpm/@radix-ui+react-toast@1.2.15_@types+react-dom@18.3.7_@types+react@18.3.27__@types+react_cb101a7507c8cedc467cf0308b5ee9a2/node_modules/@radix-ui/react-toast"
      },
      "@radix-ui/react-tooltip": {
        "from": "@radix-ui/react-tooltip",
        "version": "1.2.8",
        "resolved": "https://registry.npmjs.org/@radix-ui/react-tooltip/-/react-tooltip-1.2.8.tgz",
        "path": "/home/jhonslife/CICLOGIRO/GIRO/node_modules/.pnpm/@radix-ui+react-tooltip@1.2.8_@types+react-dom@18.3.7_@types+react@18.3.27__@types+reac_aced610d253c20559c8767bd1bee51a9/node_modules/@radix-ui/react-tooltip"
      },
      "@tanstack/react-query": {
        "from": "@tanstack/react-query",
        "version": "5.90.19",
        "resolved": "https://registry.npmjs.org/@tanstack/react-query/-/react-query-5.90.19.tgz",
        "path": "/home/jhonslife/CICLOGIRO/GIRO/node_modules/.pnpm/@tanstack+react-query@5.90.19_react@18.3.1/node_modules/@tanstack/react-query"
      },
      "@tanstack/react-table": {
        "from": "@tanstack/react-table",
        "version": "8.21.3",
        "resolved": "https://registry.npmjs.org/@tanstack/react-table/-/react-table-8.21.3.tgz",
        "path": "/home/jhonslife/CICLOGIRO/GIRO/node_modules/.pnpm/@tanstack+react-table@8.21.3_react-dom@18.3.1_react@18.3.1__react@18.3.1/node_modules/@tanstack/react-table"
      },
      "@tauri-apps/api": {
        "from": "@tauri-apps/api",
        "version": "2.9.1",
        "resolved": "https://registry.npmjs.org/@tauri-apps/api/-/api-2.9.1.tgz",
        "path": "/home/jhonslife/CICLOGIRO/GIRO/node_modules/.pnpm/@tauri-apps+api@2.9.1/node_modules/@tauri-apps/api"
      },
      "@tauri-apps/cli": {
        "from": "@tauri-apps/cli",
        "version": "2.9.6",
        "resolved": "https://registry.npmjs.org/@tauri-apps/cli/-/cli-2.9.6.tgz",
        "path": "/home/jhonslife/CICLOGIRO/GIRO/node_modules/.pnpm/@tauri-apps+cli@2.9.6/node_modules/@tauri-apps/cli"
      },
      "@tauri-apps/plugin-dialog": {
        "from": "@tauri-apps/plugin-dialog",
        "version": "2.4.2",
        "resolved": "https://registry.npmjs.org/@tauri-apps/plugin-dialog/-/plugin-dialog-2.4.2.tgz",
        "path": "/home/jhonslife/CICLOGIRO/GIRO/node_modules/.pnpm/@tauri-apps+plugin-dialog@2.4.2/node_modules/@tauri-apps/plugin-dialog"
      },
      "@tauri-apps/plugin-fs": {
        "from": "@tauri-apps/plugin-fs",
        "version": "2.4.5",
        "resolved": "https://registry.npmjs.org/@tauri-apps/plugin-fs/-/plugin-fs-2.4.5.tgz",
        "path": "/home/jhonslife/CICLOGIRO/GIRO/node_modules/.pnpm/@tauri-apps+plugin-fs@2.4.5/node_modules/@tauri-apps/plugin-fs"
      },
      "@tauri-apps/plugin-process": {
        "from": "@tauri-apps/plugin-process",
        "version": "2.3.1",
        "resolved": "https://registry.npmjs.org/@tauri-apps/plugin-process/-/plugin-process-2.3.1.tgz",
        "path": "/home/jhonslife/CICLOGIRO/GIRO/node_modules/.pnpm/@tauri-apps+plugin-process@2.3.1/node_modules/@tauri-apps/plugin-process"
      },
      "@tauri-apps/plugin-updater": {
        "from": "@tauri-apps/plugin-updater",
        "version": "2.9.0",
        "resolved": "https://registry.npmjs.org/@tauri-apps/plugin-updater/-/plugin-updater-2.9.0.tgz",
        "path": "/home/jhonslife/CICLOGIRO/GIRO/node_modules/.pnpm/@tauri-apps+plugin-updater@2.9.0/node_modules/@tauri-apps/plugin-updater"
      },
      "class-variance-authority": {
        "from": "class-variance-authority",
        "version": "0.7.1",
        "resolved": "https://registry.npmjs.org/class-variance-authority/-/class-variance-authority-0.7.1.tgz",
        "path": "/home/jhonslife/CICLOGIRO/GIRO/node_modules/.pnpm/class-variance-authority@0.7.1/node_modules/class-variance-authority"
      },
      "clsx": {
        "from": "clsx",
        "version": "2.1.1",
        "resolved": "https://registry.npmjs.org/clsx/-/clsx-2.1.1.tgz",
        "path": "/home/jhonslife/CICLOGIRO/GIRO/node_modules/.pnpm/clsx@2.1.1/node_modules/clsx"
      },
      "cmdk": {
        "from": "cmdk",
        "version": "1.1.1",
        "resolved": "https://registry.npmjs.org/cmdk/-/cmdk-1.1.1.tgz",
        "path": "/home/jhonslife/CICLOGIRO/GIRO/node_modules/.pnpm/cmdk@1.1.1_@types+react-dom@18.3.7_@types+react@18.3.27__@types+react@18.3.27_react-dom_432f7245dc8bab9f07ec6fe8c80615a1/node_modules/cmdk"
      },
      "date-fns": {
        "from": "date-fns",
        "version": "4.1.0",
        "resolved": "https://registry.npmjs.org/date-fns/-/date-fns-4.1.0.tgz",
        "path": "/home/jhonslife/CICLOGIRO/GIRO/node_modules/.pnpm/date-fns@4.1.0/node_modules/date-fns"
      },
      "framer-motion": {
        "from": "framer-motion",
        "version": "11.18.2",
        "resolved": "https://registry.npmjs.org/framer-motion/-/framer-motion-11.18.2.tgz",
        "path": "/home/jhonslife/CICLOGIRO/GIRO/node_modules/.pnpm/framer-motion@11.18.2_react-dom@18.3.1_react@18.3.1__react@18.3.1/node_modules/framer-motion"
      },
      "lucide-react": {
        "from": "lucide-react",
        "version": "0.454.0",
        "resolved": "https://registry.npmjs.org/lucide-react/-/lucide-react-0.454.0.tgz",
        "path": "/home/jhonslife/CICLOGIRO/GIRO/node_modules/.pnpm/lucide-react@0.454.0_react@18.3.1/node_modules/lucide-react"
      },
      "react": {
        "from": "react",
        "version": "18.3.1",
        "resolved": "https://registry.npmjs.org/react/-/react-18.3.1.tgz",
        "path": "/home/jhonslife/CICLOGIRO/GIRO/node_modules/.pnpm/react@18.3.1/node_modules/react"
      },
      "react-day-picker": {
        "from": "react-day-picker",
        "version": "9.13.0",
        "resolved": "https://registry.npmjs.org/react-day-picker/-/react-day-picker-9.13.0.tgz",
        "path": "/home/jhonslife/CICLOGIRO/GIRO/node_modules/.pnpm/react-day-picker@9.13.0_react@18.3.1/node_modules/react-day-picker"
      },
      "react-dom": {
        "from": "react-dom",
        "version": "18.3.1",
        "resolved": "https://registry.npmjs.org/react-dom/-/react-dom-18.3.1.tgz",
        "path": "/home/jhonslife/CICLOGIRO/GIRO/node_modules/.pnpm/react-dom@18.3.1_react@18.3.1/node_modules/react-dom"
      },
      "react-hook-form": {
        "from": "react-hook-form",
        "version": "7.71.1",
        "resolved": "https://registry.npmjs.org/react-hook-form/-/react-hook-form-7.71.1.tgz",
        "path": "/home/jhonslife/CICLOGIRO/GIRO/node_modules/.pnpm/react-hook-form@7.71.1_react@18.3.1/node_modules/react-hook-form"
      },
      "react-router-dom": {
        "from": "react-router-dom",
        "version": "6.30.3",
        "resolved": "https://registry.npmjs.org/react-router-dom/-/react-router-dom-6.30.3.tgz",
        "path": "/home/jhonslife/CICLOGIRO/GIRO/node_modules/.pnpm/react-router-dom@6.30.3_react-dom@18.3.1_react@18.3.1__react@18.3.1/node_modules/react-router-dom"
      },
      "recharts": {
        "from": "recharts",
        "version": "2.15.4",
        "resolved": "https://registry.npmjs.org/recharts/-/recharts-2.15.4.tgz",
        "path": "/home/jhonslife/CICLOGIRO/GIRO/node_modules/.pnpm/recharts@2.15.4_react-dom@18.3.1_react@18.3.1__react@18.3.1/node_modules/recharts"
      },
      "sonner": {
        "from": "sonner",
        "version": "2.0.7",
        "resolved": "https://registry.npmjs.org/sonner/-/sonner-2.0.7.tgz",
        "path": "/home/jhonslife/CICLOGIRO/GIRO/node_modules/.pnpm/sonner@2.0.7_react-dom@18.3.1_react@18.3.1__react@18.3.1/node_modules/sonner"
      },
      "tailwind-merge": {
        "from": "tailwind-merge",
        "version": "2.6.0",
        "resolved": "https://registry.npmjs.org/tailwind-merge/-/tailwind-merge-2.6.0.tgz",
        "path": "/home/jhonslife/CICLOGIRO/GIRO/node_modules/.pnpm/tailwind-merge@2.6.0/node_modules/tailwind-merge"
      },
      "tailwindcss-animate": {
        "from": "tailwindcss-animate",
        "version": "1.0.7",
        "resolved": "https://registry.npmjs.org/tailwindcss-animate/-/tailwindcss-animate-1.0.7.tgz",
        "path": "/home/jhonslife/CICLOGIRO/GIRO/node_modules/.pnpm/tailwindcss-animate@1.0.7_tailwindcss@3.4.19_tsx@4.21.0_/node_modules/tailwindcss-animate"
      },
      "zod": {
        "from": "zod",
        "version": "3.25.76",
        "resolved": "https://registry.npmjs.org/zod/-/zod-3.25.76.tgz",
        "path": "/home/jhonslife/CICLOGIRO/GIRO/node_modules/.pnpm/zod@3.25.76/node_modules/zod"
      },
      "zustand": {
        "from": "zustand",
        "version": "5.0.10",
        "resolved": "https://registry.npmjs.org/zustand/-/zustand-5.0.10.tgz",
        "path": "/home/jhonslife/CICLOGIRO/GIRO/node_modules/.pnpm/zustand@5.0.10_@types+react@18.3.27_react@18.3.1_use-sync-external-store@1.6.0_react@18.3.1_/node_modules/zustand"
      }
    },
    "devDependencies": {
      "@playwright/test": {
        "from": "@playwright/test",
        "version": "1.57.0",
        "resolved": "https://registry.npmjs.org/@playwright/test/-/test-1.57.0.tgz",
        "path": "/home/jhonslife/CICLOGIRO/GIRO/node_modules/.pnpm/@playwright+test@1.57.0/node_modules/@playwright/test"
      },
      "@testing-library/dom": {
        "from": "@testing-library/dom",
        "version": "10.4.1",
        "resolved": "https://registry.npmjs.org/@testing-library/dom/-/dom-10.4.1.tgz",
        "path": "/home/jhonslife/CICLOGIRO/GIRO/node_modules/.pnpm/@testing-library+dom@10.4.1/node_modules/@testing-library/dom"
      },
      "@testing-library/jest-dom": {
        "from": "@testing-library/jest-dom",
        "version": "6.9.1",
        "resolved": "https://registry.npmjs.org/@testing-library/jest-dom/-/jest-dom-6.9.1.tgz",
        "path": "/home/jhonslife/CICLOGIRO/GIRO/node_modules/.pnpm/@testing-library+jest-dom@6.9.1/node_modules/@testing-library/jest-dom"
      },
      "@testing-library/react": {
        "from": "@testing-library/react",
        "version": "16.3.2",
        "resolved": "https://registry.npmjs.org/@testing-library/react/-/react-16.3.2.tgz",
        "path": "/home/jhonslife/CICLOGIRO/GIRO/node_modules/.pnpm/@testing-library+react@16.3.2_@testing-library+dom@10.4.1_@types+react-dom@18.3.7_@type_bee4ed7d26d8655619a432101f08c8d9/node_modules/@testing-library/react"
      },
      "@testing-library/user-event": {
        "from": "@testing-library/user-event",
        "version": "14.6.1",
        "resolved": "https://registry.npmjs.org/@testing-library/user-event/-/user-event-14.6.1.tgz",
        "path": "/home/jhonslife/CICLOGIRO/GIRO/node_modules/.pnpm/@testing-library+user-event@14.6.1_@testing-library+dom@10.4.1/node_modules/@testing-library/user-event"
      },
      "@types/node": {
        "from": "@types/node",
        "version": "22.19.7",
        "resolved": "https://registry.npmjs.org/@types/node/-/node-22.19.7.tgz",
        "path": "/home/jhonslife/CICLOGIRO/GIRO/node_modules/.pnpm/@types+node@22.19.7/node_modules/@types/node"
      },
      "@types/react": {
        "from": "@types/react",
        "version": "18.3.27",
        "resolved": "https://registry.npmjs.org/@types/react/-/react-18.3.27.tgz",
        "path": "/home/jhonslife/CICLOGIRO/GIRO/node_modules/.pnpm/@types+react@18.3.27/node_modules/@types/react"
      },
      "@types/react-dom": {
        "from": "@types/react-dom",
        "version": "18.3.7",
        "resolved": "https://registry.npmjs.org/@types/react-dom/-/react-dom-18.3.7.tgz",
        "path": "/home/jhonslife/CICLOGIRO/GIRO/node_modules/.pnpm/@types+react-dom@18.3.7_@types+react@18.3.27/node_modules/@types/react-dom"
      },
      "@typescript-eslint/eslint-plugin": {
        "from": "@typescript-eslint/eslint-plugin",
        "version": "8.53.0",
        "resolved": "https://registry.npmjs.org/@typescript-eslint/eslint-plugin/-/eslint-plugin-8.53.0.tgz",
        "path": "/home/jhonslife/CICLOGIRO/GIRO/node_modules/.pnpm/@typescript-eslint+eslint-plugin@8.53.0_@typescript-eslint+parser@8.53.0_eslint@9.39.2__6056ac733c55ae46a8abde5026c58bb8/node_modules/@typescript-eslint/eslint-plugin"
      },
      "@typescript-eslint/parser": {
        "from": "@typescript-eslint/parser",
        "version": "8.53.0",
        "resolved": "https://registry.npmjs.org/@typescript-eslint/parser/-/parser-8.53.0.tgz",
        "path": "/home/jhonslife/CICLOGIRO/GIRO/node_modules/.pnpm/@typescript-eslint+parser@8.53.0_eslint@9.39.2_jiti@1.21.7__typescript@5.9.3/node_modules/@typescript-eslint/parser"
      },
      "@vitejs/plugin-react": {
        "from": "@vitejs/plugin-react",
        "version": "4.7.0",
        "resolved": "https://registry.npmjs.org/@vitejs/plugin-react/-/plugin-react-4.7.0.tgz",
        "path": "/home/jhonslife/CICLOGIRO/GIRO/node_modules/.pnpm/@vitejs+plugin-react@4.7.0_vite@5.4.21_@types+node@22.19.7_/node_modules/@vitejs/plugin-react"
      },
      "@vitest/coverage-istanbul": {
        "from": "@vitest/coverage-istanbul",
        "version": "2.1.9",
        "resolved": "https://registry.npmjs.org/@vitest/coverage-istanbul/-/coverage-istanbul-2.1.9.tgz",
        "path": "/home/jhonslife/CICLOGIRO/GIRO/node_modules/.pnpm/@vitest+coverage-istanbul@2.1.9_vitest@2.1.9/node_modules/@vitest/coverage-istanbul"
      },
      "@vitest/coverage-v8": {
        "from": "@vitest/coverage-v8",
        "version": "2.1.9",
        "resolved": "https://registry.npmjs.org/@vitest/coverage-v8/-/coverage-v8-2.1.9.tgz",
        "path": "/home/jhonslife/CICLOGIRO/GIRO/node_modules/.pnpm/@vitest+coverage-v8@2.1.9_vitest@2.1.9/node_modules/@vitest/coverage-v8"
      },
      "@vitest/ui": {
        "from": "@vitest/ui",
        "version": "2.1.9",
        "resolved": "https://registry.npmjs.org/@vitest/ui/-/ui-2.1.9.tgz",
        "path": "/home/jhonslife/CICLOGIRO/GIRO/node_modules/.pnpm/@vitest+ui@2.1.9_vitest@2.1.9/node_modules/@vitest/ui"
      },
      "autoprefixer": {
        "from": "autoprefixer",
        "version": "10.4.23",
        "resolved": "https://registry.npmjs.org/autoprefixer/-/autoprefixer-10.4.23.tgz",
        "path": "/home/jhonslife/CICLOGIRO/GIRO/node_modules/.pnpm/autoprefixer@10.4.23_postcss@8.5.6/node_modules/autoprefixer"
      },
      "eslint": {
        "from": "eslint",
        "version": "9.39.2",
        "resolved": "https://registry.npmjs.org/eslint/-/eslint-9.39.2.tgz",
        "path": "/home/jhonslife/CICLOGIRO/GIRO/node_modules/.pnpm/eslint@9.39.2_jiti@1.21.7/node_modules/eslint"
      },
      "eslint-plugin-react-hooks": {
        "from": "eslint-plugin-react-hooks",
        "version": "5.2.0",
        "resolved": "https://registry.npmjs.org/eslint-plugin-react-hooks/-/eslint-plugin-react-hooks-5.2.0.tgz",
        "path": "/home/jhonslife/CICLOGIRO/GIRO/node_modules/.pnpm/eslint-plugin-react-hooks@5.2.0_eslint@9.39.2_jiti@1.21.7_/node_modules/eslint-plugin-react-hooks"
      },
      "eslint-plugin-react-refresh": {
        "from": "eslint-plugin-react-refresh",
        "version": "0.4.26",
        "resolved": "https://registry.npmjs.org/eslint-plugin-react-refresh/-/eslint-plugin-react-refresh-0.4.26.tgz",
        "path": "/home/jhonslife/CICLOGIRO/GIRO/node_modules/.pnpm/eslint-plugin-react-refresh@0.4.26_eslint@9.39.2_jiti@1.21.7_/node_modules/eslint-plugin-react-refresh"
      },
      "jsdom": {
        "from": "jsdom",
        "version": "25.0.1",
        "resolved": "https://registry.npmjs.org/jsdom/-/jsdom-25.0.1.tgz",
        "path": "/home/jhonslife/CICLOGIRO/GIRO/node_modules/.pnpm/jsdom@25.0.1/node_modules/jsdom"
      },
      "postcss": {
        "from": "postcss",
        "version": "8.5.6",
        "resolved": "https://registry.npmjs.org/postcss/-/postcss-8.5.6.tgz",
        "path": "/home/jhonslife/CICLOGIRO/GIRO/node_modules/.pnpm/postcss@8.5.6/node_modules/postcss"
      },
      "tailwindcss": {
        "from": "tailwindcss",
        "version": "3.4.19",
        "resolved": "https://registry.npmjs.org/tailwindcss/-/tailwindcss-3.4.19.tgz",
        "path": "/home/jhonslife/CICLOGIRO/GIRO/node_modules/.pnpm/tailwindcss@3.4.19_tsx@4.21.0/node_modules/tailwindcss"
      },
      "typescript": {
        "from": "typescript",
        "version": "5.9.3",
        "resolved": "https://registry.npmjs.org/typescript/-/typescript-5.9.3.tgz",
        "path": "/home/jhonslife/CICLOGIRO/GIRO/node_modules/.pnpm/typescript@5.9.3/node_modules/typescript"
      },
      "vite": {
        "from": "vite",
        "version": "5.4.21",
        "resolved": "https://registry.npmjs.org/vite/-/vite-5.4.21.tgz",
        "path": "/home/jhonslife/CICLOGIRO/GIRO/node_modules/.pnpm/vite@5.4.21_@types+node@22.19.7/node_modules/vite"
      },
      "vitest": {
        "from": "vitest",
        "version": "2.1.9",
        "resolved": "https://registry.npmjs.org/vitest/-/vitest-2.1.9.tgz",
        "path": "/home/jhonslife/CICLOGIRO/GIRO/node_modules/.pnpm/vitest@2.1.9_@types+node@22.19.7_@vitest+ui@2.1.9_jsdom@25.0.1/node_modules/vitest"
      }
    }
  }
]
